LICENSE
MANIFEST.in
README.md
setup.py
HybridCORELS/HybridCORELS.py
HybridCORELS/PrefixCorels.py
HybridCORELS/README.txt
HybridCORELS/VERSION
HybridCORELS/__init__.py
HybridCORELS/_prefix_corels.cpp
HybridCORELS/_prefix_corels.pyx
HybridCORELS/utils.py
HybridCORELS.egg-info/PKG-INFO
HybridCORELS.egg-info/SOURCES.txt
HybridCORELS.egg-info/dependency_links.txt
HybridCORELS.egg-info/requires.txt
HybridCORELS.egg-info/top_level.txt
HybridCORELS/src/utils.cpp
HybridCORELS/src/utils.hh
HybridCORELS/src/corels/src/alloc.h
HybridCORELS/src/corels/src/cache.cpp
HybridCORELS/src/corels/src/cache.h
HybridCORELS/src/corels/src/corels.cpp
HybridCORELS/src/corels/src/main.cpp
HybridCORELS/src/corels/src/pmap.cpp
HybridCORELS/src/corels/src/pmap.h
HybridCORELS/src/corels/src/queue.h
HybridCORELS/src/corels/src/rule.h
HybridCORELS/src/corels/src/rulelib.cpp
HybridCORELS/src/corels/src/run.cpp
HybridCORELS/src/corels/src/run.h
HybridCORELS/src/corels/src/utils.cpp
HybridCORELS/src/corels/src/utils.h