Metadata-Version: 2.1
Name: HybridCORELS
Version: 0.53
Summary: Python module for Hybrid Rule Lists/Black-Box models, based on the Python binding of the CORELS algorithm
Home-page: https://github.com/ferryjul/HybridCORELS
Author: Julien Ferry, Gabriel Laberge, Ulrich Aïvodji
Author-email: jferry@laas.fr
License: GNU General Public License v3 (GPLv3)
Classifier: Programming Language :: C++
Classifier: License :: OSI Approved :: GNU General Public License v3 (GPLv3)
Classifier: Operating System :: OS Independent
Requires-Python: >=3
License-File: LICENSE
